Metadata-Version: 1.1
Name: couleur
Version: 0.7.1
Summary: ANSI terminal tool for python, colored shell and other handy fancy features
Home-page: http://github.com/gabrielfalcao/couleur
Author: Gabriel Falcao
Author-email: gabriel@nacaolivre.org
License: UNKNOWN
Platform: UNKNOWN
Classifier: Development Status :: 5 - Production/Stable
Classifier: License :: OSI Approved :: Apache Software License
Classifier: Operating System :: POSIX
Classifier: Programming Language :: Python
Classifier: Programming Language :: Python :: 2
